{
  "top": [
    "Bari",
    "Palermo",
    "Genova"
  ],
  "ruote": {
    "Bari": {
      "ultima": [
        41,
        9,
        64,
        6,
        61
      ],
      "ambo": [
        66,
        67
      ],
      "score": 464.39
    },
    "Cagliari": {
      "ultima": [
        8,
        7,
        32,
        84,
        21
      ],
      "ambo": [
        41,
        87
      ],
      "score": 367.02
    },
    "Firenze": {
      "ultima": [
        71,
        80,
        69,
        60,
        56
      ],
      "ambo": [
        28,
        33
      ],
      "score": 394.1
    },
    "Genova": {
      "ultima": [
        83,
        49,
        67,
        54,
        47
      ],
      "ambo": [
        3,
        66
      ],
      "score": 401.38
    },
    "Milano": {
      "ultima": [
        17,
        33,
        51,
        53,
        4
      ],
      "ambo": [
        77,
        88
      ],
      "score": 396.65
    },
    "Napoli": {
      "ultima": [
        26,
        82,
        7,
        73,
        53
      ],
      "ambo": [
        1,
        40
      ],
      "score": 392.21
    },
    "Palermo": {
      "ultima": [
        56,
        17,
        41,
        21,
        77
      ],
      "ambo": [
        45,
        90
      ],
      "score": 409.04
    },
    "Roma": {
      "ultima": [
        38,
        30,
        39,
        15,
        6
      ],
      "ambo": [
        17,
        37
      ],
      "score": 372.48
    },
    "Torino": {
      "ultima": [
        45,
        39,
        89,
        80,
        64
      ],
      "ambo": [
        49,
        65
      ],
      "score": 387.79
    },
    "Venezia": {
      "ultima": [
        40,
        71,
        78,
        17,
        90
      ],
      "ambo": [
        33,
        79
      ],
      "score": 355.04
    }
  },
  "giocate": [
    {
      "ruota": "Bari",
      "ambo": [
        66,
        67
      ]
    },
    {
      "ruota": "Palermo",
      "ambo": [
        45,
        90
      ]
    },
    {
      "ruota": "Genova",
      "ambo": [
        3,
        66
      ]
    }
  ],
  "jolly": {
    "ruota": "Napoli",
    "ambo": [
      66,
      67
    ]
  }
}