{
  "ultime_estrazioni": {
    "Bari": [
      80,
      54,
      31,
      75,
      71
    ],
    "Cagliari": [
      38,
      23,
      54,
      50,
      89
    ],
    "Firenze": [
      57,
      73,
      82,
      35,
      45
    ],
    "Genova": [
      58,
      70,
      12,
      65,
      85
    ],
    "Milano": [
      82,
      20,
      35,
      14,
      8
    ],
    "Napoli": [
      48,
      65,
      79,
      52,
      16
    ],
    "Palermo": [
      5,
      60,
      56,
      1,
      25
    ],
    "Roma": [
      65,
      12,
      73,
      3,
      49
    ],
    "Torino": [
      39,
      43,
      44,
      36,
      67
    ],
    "Venezia": [
      71,
      76,
      49,
      6,
      56
    ]
  },
  "ruote_gemelle": {
    "Bari": "Torino",
    "Cagliari": "Roma",
    "Firenze": "Roma",
    "Genova": "Milano",
    "Milano": "Napoli",
    "Napoli": "Milano",
    "Palermo": "Roma",
    "Roma": "Cagliari",
    "Torino": "Bari",
    "Venezia": "Milano"
  },
  "top": [
    {
      "ambo": [
        5,
        41
      ],
      "raw_score": 84.80000000000001,
      "prob": 100.0
    },
    {
      "ambo": [
        8,
        41
      ],
      "raw_score": 84.80000000000001,
      "prob": 100.0
    },
    {
      "ambo": [
        4,
        41
      ],
      "raw_score": 82.80000000000001,
      "prob": 97.64
    }
  ],
  "ambi": [
    {
      "ambo": [
        5,
        41
      ],
      "raw_score": 84.80000000000001,
      "prob": 100.0
    },
    {
      "ambo": [
        8,
        41
      ],
      "raw_score": 84.80000000000001,
      "prob": 100.0
    },
    {
      "ambo": [
        4,
        41
      ],
      "raw_score": 82.80000000000001,
      "prob": 97.64
    },
    {
      "ambo": [
        7,
        41
      ],
      "raw_score": 82.80000000000001,
      "prob": 97.64
    },
    {
      "ambo": [
        9,
        41
      ],
      "raw_score": 82.80000000000001,
      "prob": 97.64
    },
    {
      "ambo": [
        12,
        41
      ],
      "raw_score": 82.80000000000001,
      "prob": 97.64
    },
    {
      "ambo": [
        18,
        41
      ],
      "raw_score": 82.80000000000001,
      "prob": 97.64
    },
    {
      "ambo": [
        23,
        41
      ],
      "raw_score": 82.80000000000001,
      "prob": 97.64
    },
    {
      "ambo": [
        25,
        41
      ],
      "raw_score": 82.80000000000001,
      "prob": 97.64
    },
    {
      "ambo": [
        41,
        45
      ],
      "raw_score": 82.80000000000001,
      "prob": 97.64
    },
    {
      "ambo": [
        41,
        54
      ],
      "raw_score": 82.80000000000001,
      "prob": 97.64
    },
    {
      "ambo": [
        41,
        55
      ],
      "raw_score": 82.80000000000001,
      "prob": 97.64
    },
    {
      "ambo": [
        41,
        60
      ],
      "raw_score": 82.80000000000001,
      "prob": 97.64
    },
    {
      "ambo": [
        41,
        67
      ],
      "raw_score": 82.80000000000001,
      "prob": 97.64
    },
    {
      "ambo": [
        41,
        78
      ],
      "raw_score": 82.80000000000001,
      "prob": 97.64
    },
    {
      "ambo": [
        41,
        79
      ],
      "raw_score": 82.80000000000001,
      "prob": 97.64
    },
    {
      "ambo": [
        41,
        83
      ],
      "raw_score": 82.80000000000001,
      "prob": 97.64
    },
    {
      "ambo": [
        41,
        90
      ],
      "raw_score": 82.80000000000001,
      "prob": 97.64
    },
    {
      "ambo": [
        1,
        41
      ],
      "raw_score": 80.80000000000001,
      "prob": 95.28
    },
    {
      "ambo": [
        2,
        41
      ],
      "raw_score": 80.80000000000001,
      "prob": 95.28
    }
  ]
}