{
  "ruote": [
    {
      "ruota": "Bari",
      "ultima": [
        51,
        62,
        27,
        44,
        28
      ],
      "numeri_caldi": [
        24,
        37
      ],
      "ambo_forte": "24-37",
      "ciclometria": "6 | 9",
      "saturazione": 0.56,
      "indice": 1.44
    },
    {
      "ruota": "Cagliari",
      "ultima": [
        73,
        24,
        23,
        48,
        43
      ],
      "numeri_caldi": [
        49,
        31
      ],
      "ambo_forte": "49-31",
      "ciclometria": "8 | 7",
      "saturazione": 0.56,
      "indice": 1.44
    },
    {
      "ruota": "Firenze",
      "ultima": [
        46,
        15,
        72,
        52,
        31
      ],
      "numeri_caldi": [
        25,
        50
      ],
      "ambo_forte": "25-50",
      "ciclometria": "7 | 7",
      "saturazione": 0.56,
      "indice": 1.47
    },
    {
      "ruota": "Genova",
      "ultima": [
        17,
        9,
        29,
        19,
        27
      ],
      "numeri_caldi": [
        43,
        26
      ],
      "ambo_forte": "43-26",
      "ciclometria": "6 | 10",
      "saturazione": 0.56,
      "indice": 1.41
    },
    {
      "ruota": "Milano",
      "ultima": [
        6,
        70,
        5,
        76,
        79
      ],
      "numeri_caldi": [
        21,
        29
      ],
      "ambo_forte": "21-29",
      "ciclometria": "7 | 8",
      "saturazione": 0.56,
      "indice": 1.38
    },
    {
      "ruota": "Napoli",
      "ultima": [
        51,
        16,
        26,
        11,
        48
      ],
      "numeri_caldi": [
        65,
        76
      ],
      "ambo_forte": "65-76",
      "ciclometria": "10 | 9",
      "saturazione": 0.56,
      "indice": 1.0
    },
    {
      "ruota": "Palermo",
      "ultima": [
        88,
        57,
        76,
        84,
        9
      ],
      "numeri_caldi": [
        26,
        51
      ],
      "ambo_forte": "26-51",
      "ciclometria": "7 | 9",
      "saturazione": 0.56,
      "indice": 1.35
    },
    {
      "ruota": "Roma",
      "ultima": [
        90,
        38,
        32,
        69,
        53
      ],
      "numeri_caldi": [
        67,
        14
      ],
      "ambo_forte": "67-14",
      "ciclometria": "7 | 8",
      "saturazione": 0.56,
      "indice": 1.56
    },
    {
      "ruota": "Torino",
      "ultima": [
        85,
        84,
        58,
        60,
        87
      ],
      "numeri_caldi": [
        75,
        5
      ],
      "ambo_forte": "75-5",
      "ciclometria": "9 | 11",
      "saturazione": 0.56,
      "indice": 0.9
    },
    {
      "ruota": "Venezia",
      "ultima": [
        14,
        41,
        26,
        90,
        52
      ],
      "numeri_caldi": [
        36,
        67
      ],
      "ambo_forte": "36-67",
      "ciclometria": "9 | 7",
      "saturazione": 0.56,
      "indice": 1.29
    }
  ],
  "giocate_top": [
    {
      "ruota": "Roma",
      "ambo": "67-14",
      "score": 1.56
    },
    {
      "ruota": "Firenze",
      "ambo": "25-50",
      "score": 1.47
    },
    {
      "ruota": "Bari",
      "ambo": "24-37",
      "score": 1.44
    }
  ]
}